yamlconf.py
yamlconf/__init__.py
yamlconf/about.py
yamlconf/errors.py
yamlconf/import_module.py
yamlconf/import_path.py
yamlconf/load.py
yamlconf/merge.py
yamlconf/propagate_defaults.py
yamlconf/tests/__init__.py
yamlconf/tests/test_import_path.py
yamlconf/tests/test_load.py
yamlconf/tests/test_merge.py
yamlconf/tests/test_propagate_defaults.py
yamlconf/tests/util/__init__.py
yamlconf/tests/util/submodule.py
yamlconf/tests/util/value.py
yamlconf-0.2.6.dist-info/LICENSE
yamlconf-0.2.6.dist-info/METADATA
yamlconf-0.2.6.dist-info/WHEEL
yamlconf-0.2.6.dist-info/top_level.txt
yamlconf-0.2.6.dist-info/RECORD
